danio/__init__.py
danio/aiopg.py
danio/asyncpg.py
danio/database.py
danio/exception.py
danio/manage.py
danio/model.py
danio/mysql.py
danio/schema.py
danio/sqlite.py
danio/utils.py
danio-0.5.1.dist-info/LICENSE
danio-0.5.1.dist-info/METADATA
danio-0.5.1.dist-info/WHEEL
danio-0.5.1.dist-info/RECORD
